zshgpt/__about__.py
zshgpt/__init__.py
zshgpt/__main__.py
zshgpt/settings.py
zshgpt/cli/__init__.py
zshgpt/util/assistant.py
zshgpt/util/chat_util.py
zshgpt/util/client.py
zshgpt/util/messages.py
zshgpt-1.3.1.dist-info/METADATA
zshgpt-1.3.1.dist-info/WHEEL
zshgpt-1.3.1.dist-info/entry_points.txt
zshgpt-1.3.1.dist-info/licenses/LICENSE
zshgpt-1.3.1.dist-info/licenses/LICENSE.txt
zshgpt-1.3.1.dist-info/RECORD
