Metadata-Version: 2.3
Name: zshgpt
Version: 1.3.1
Summary: Level up z shell with GPT
Project-URL: Documentation, https://github.com/AndersSteenNilsen/zshgpt#readme
Project-URL: Issues, https://github.com/AndersSteenNilsen/zshgpt/issues
Project-URL: Source, https://github.com/AndersSteenNilsen/zshgpt
Author-email: Anders Steen <asteennilsen@gmail.com>
License-Expression: MIT
License-File: LICENSE
License-File: LICENSE.txt
Classifier: Development Status :: 5 - Production/Stable
Classifier: Framework :: Hatch
Classifier: License :: OSI Approved :: MIT License
Classifier: Programming Language :: Python
Classifier: Programming Language :: Python :: 3.8
Classifier: Programming Language :: Python :: 3.9
Classifier: Programming Language :: Python :: 3.10
Classifier: Programming Language :: Python :: 3.11
Classifier: Programming Language :: Python :: 3.12
Classifier: Programming Language :: Python :: Implementation :: CPython
Classifier: Programming Language :: Python :: Implementation :: PyPy
Classifier: Topic :: Utilities
Requires-Python: >=3.8
Requires-Dist: click
Requires-Dist: openai~=1.2.4
Requires-Dist: pydantic-settings
